{
  "version": "1.0.43",
  "channel": "stable",
  "required": true,
  "url": "https://github.com/thuan04102001/AIAUTODO-release/releases/download/v1.0.43/AI.AUTODO.Setup.1.0.43.exe",
  "sha256": "2a160b61e67aaa03bb14283c6a45cfb137d5d3d93ecd45388a4a6c6d0c399baa",
  "size": 628245191,
  "published_at": "2026-07-02T12:42:40+00:00",
  "changelog": [
    "Fix GPU pack layout overflow and refresh button wrapping.",
    "Fix stale quick-patch restart state after update.",
    "Keep stable Windows identity and shortcut behavior for updates.",
    "Fix Fanpage credential labels and default expanded sidebar."
  ],
  "patch": {
    "version": "1.0.43",
    "url": "https://github.com/thuan04102001/AIAUTODO-release/releases/download/v1.0.43/AI.AUTODO.App.Patch.1.0.43.zip",
    "sha256": "d24f6529f811f3fa5ace21b3e832c49d39412cb80fe9e27d10135b7294d12506",
    "size": 376483159
  }
}
